{
  "generated_at": "2026-05-02T11:12:59.914222+00:00",
  "source": "data.gouv.fr — DECP consolidés",
  "source_url": "https://www.data.gouv.fr/datasets/donnees-essentielles-de-la-commande-publique-consolidees-format-tabulaire/",
  "source_resource_id": "22847056-61df-452d-837d-8b8ceadbfc52",
  "commune": {
    "slug": "nantes",
    "nom": "Nantes",
    "siren": "214401093"
  },
  "aggregates": {
    "total_count": 1563,
    "total_montant": 505695597,
    "coverage_pct": 80.9,
    "n_with_montant": 1264,
    "duplicates_dropped": 518,
    "outliers_dropped": 0,
    "sentinels_dropped": 0,
    "max_plausible_montant": 200000000,
    "by_year": [
      {
        "year": 2020,
        "montant": 3004177,
        "count": 35
      },
      {
        "year": 2021,
        "montant": 38667194,
        "count": 305
      },
      {
        "year": 2022,
        "montant": 10254579,
        "count": 234
      },
      {
        "year": 2023,
        "montant": 11903786,
        "count": 78
      },
      {
        "year": 2024,
        "montant": 143916959,
        "count": 213
      },
      {
        "year": 2025,
        "montant": 91881079,
        "count": 420
      },
      {
        "year": 2026,
        "montant": 206067824,
        "count": 278
      }
    ],
    "top_titulaires_window_years": 5,
    "top_titulaires": [
      {
        "id": "32671449000041",
        "nom": "DOMUS ARCHITECTURE",
        "montant": 28750000,
        "count": 3
      },
      {
        "id": "39825193400038",
        "nom": "ADC PROPRETE",
        "montant": 21065097,
        "count": 5
      },
      {
        "id": "84895023400049",
        "nom": "MCA MAEL CLAVIER ARCHITECTURE",
        "montant": 21000000,
        "count": 2
      },
      {
        "id": "45190406400024",
        "nom": "AURA",
        "montant": 21000000,
        "count": 2
      },
      {
        "id": "52540335800068",
        "nom": "LEMOAL ARCHITECTES",
        "montant": 21000000,
        "count": 2
      },
      {
        "id": "40001977400027",
        "nom": "ARCHITECTURES - CHABENES ET SCOTT",
        "montant": 16500000,
        "count": 1
      },
      {
        "id": "41068325400115",
        "nom": "LEO LAGRANGE OUEST",
        "montant": 11302916,
        "count": 2
      },
      {
        "id": "78821382500987",
        "nom": "SERIS SECURITY",
        "montant": 8429410,
        "count": 2
      },
      {
        "id": "42900108400046",
        "nom": "PIERLUIGI PERICOLO",
        "montant": 8000000,
        "count": 3
      },
      {
        "id": "52225711200014",
        "nom": "KOMOREBI",
        "montant": 7750000,
        "count": 1
      },
      {
        "id": "80023743000023",
        "nom": "BIGRE",
        "montant": 7750000,
        "count": 1
      },
      {
        "id": "43884541400038",
        "nom": "2LM",
        "montant": 7750000,
        "count": 1
      },
      {
        "id": "50825195600027",
        "nom": "SOCIETE D'EXPERTISES ET CONSEILS EN COUVERTURE CENTRE OUEST - SECC CENTRE OUEST",
        "montant": 7750000,
        "count": 1
      },
      {
        "id": "44452352600945",
        "nom": "ARTELIA",
        "montant": 7750000,
        "count": 1
      },
      {
        "id": "453088361CLI",
        "nom": "?",
        "montant": 7750000,
        "count": 1
      }
    ]
  },
  "notes_fr": "Marchés publics filtrés par SIREN acheteur (214401093). Couverture estimée de la qualité montant : 80.9% des marchés ont un montant non-nul renseigné. La DECP au national est connue pour avoir une qualité variable selon les acheteurs ; les chiffres ci-dessous sont bruts, non corrigés.",
  "notes_en": "Public procurement filtered by buyer SIREN (214401093). Estimated quality coverage: 80.9% of contracts have a non-zero amount. DECP is known for variable quality across buyers; numbers below are raw, unadjusted."
}