{
  "generated_at": "2026-05-01T22:19:35.538445+00:00",
  "source": "OFGL — ofgl-base-communes-consolidee",
  "source_url": "https://data.ofgl.fr/explore/dataset/ofgl-base-communes-consolidee/",
  "perimeter_label_fr": "Comptes consolidés — OFGL (M14 + M57 harmonisés)",
  "perimeter_label_en": "Consolidated accounts — OFGL (M14 + M57 harmonised)",
  "city": {
    "slug": "strasbourg",
    "nom": "Strasbourg",
    "code_insee": "67482",
    "siren": "216704825",
    "dep_name": "Bas-Rhin",
    "reg_name": "Grand Est",
    "population_latest": 294229,
    "latest_year": 2024,
    "years": [
      2017,
      2018,
      2019,
      2020,
      2021,
      2022,
      2023,
      2024
    ],
    "series": {
      "recettes_totales": [
        {
          "year": 2017,
          "montant": 418344184,
          "eur_hab": 1490.5
        },
        {
          "year": 2018,
          "montant": 440398369,
          "eur_hab": 1564.4
        },
        {
          "year": 2019,
          "montant": 424676080,
          "eur_hab": 1497.9
        },
        {
          "year": 2020,
          "montant": 419139033,
          "eur_hab": 1477.2
        },
        {
          "year": 2021,
          "montant": 439027580,
          "eur_hab": 1526.9
        },
        {
          "year": 2022,
          "montant": 477703963,
          "eur_hab": 1646.7
        },
        {
          "year": 2023,
          "montant": 489095857,
          "eur_hab": 1666.2
        },
        {
          "year": 2024,
          "montant": 484824380,
          "eur_hab": 1647.8
        }
      ],
      "depenses_totales": [
        {
          "year": 2017,
          "montant": 412871818,
          "eur_hab": 1471.0
        },
        {
          "year": 2018,
          "montant": 421012531,
          "eur_hab": 1495.5
        },
        {
          "year": 2019,
          "montant": 459686829,
          "eur_hab": 1621.4
        },
        {
          "year": 2020,
          "montant": 444323203,
          "eur_hab": 1565.9
        },
        {
          "year": 2021,
          "montant": 463190039,
          "eur_hab": 1610.9
        },
        {
          "year": 2022,
          "montant": 489505957,
          "eur_hab": 1687.3
        },
        {
          "year": 2023,
          "montant": 537030183,
          "eur_hab": 1829.5
        },
        {
          "year": 2024,
          "montant": 532996485,
          "eur_hab": 1811.5
        }
      ],
      "encours_dette": [
        {
          "year": 2017,
          "montant": 218700327,
          "eur_hab": 779.2
        },
        {
          "year": 2018,
          "montant": 193862564,
          "eur_hab": 688.6
        },
        {
          "year": 2019,
          "montant": 202877143,
          "eur_hab": 715.6
        },
        {
          "year": 2020,
          "montant": 242219864,
          "eur_hab": 853.7
        },
        {
          "year": 2021,
          "montant": 274279639,
          "eur_hab": 953.9
        },
        {
          "year": 2022,
          "montant": 304717154,
          "eur_hab": 1050.4
        },
        {
          "year": 2023,
          "montant": 332889293,
          "eur_hab": 1134.1
        },
        {
          "year": 2024,
          "montant": 377996969,
          "eur_hab": 1284.7
        }
      ],
      "epargne_brute": [
        {
          "year": 2017,
          "montant": 37169558,
          "eur_hab": 132.4
        },
        {
          "year": 2018,
          "montant": 42428960,
          "eur_hab": 150.7
        },
        {
          "year": 2019,
          "montant": 39580476,
          "eur_hab": 139.6
        },
        {
          "year": 2020,
          "montant": 41741091,
          "eur_hab": 147.1
        },
        {
          "year": 2021,
          "montant": 38831226,
          "eur_hab": 135.1
        },
        {
          "year": 2022,
          "montant": 57127191,
          "eur_hab": 196.9
        },
        {
          "year": 2023,
          "montant": 36239915,
          "eur_hab": 123.5
        },
        {
          "year": 2024,
          "montant": 37605642,
          "eur_hab": 127.8
        }
      ],
      "capacite_financement": [
        {
          "year": 2017,
          "montant": 5472366,
          "eur_hab": 19.5
        },
        {
          "year": 2018,
          "montant": 19385839,
          "eur_hab": 68.9
        },
        {
          "year": 2019,
          "montant": -35010750,
          "eur_hab": -123.5
        },
        {
          "year": 2020,
          "montant": -25184170,
          "eur_hab": -88.8
        },
        {
          "year": 2021,
          "montant": -24162459,
          "eur_hab": -84.0
        },
        {
          "year": 2022,
          "montant": -11801994,
          "eur_hab": -40.7
        },
        {
          "year": 2023,
          "montant": -47934327,
          "eur_hab": -163.3
        },
        {
          "year": 2024,
          "montant": -48172105,
          "eur_hab": -163.7
        }
      ],
      "depenses_fonctionnement": [
        {
          "year": 2017,
          "montant": 344370075,
          "eur_hab": 1226.9
        },
        {
          "year": 2018,
          "montant": 346994450,
          "eur_hab": 1232.6
        },
        {
          "year": 2019,
          "montant": 355710472,
          "eur_hab": 1254.6
        },
        {
          "year": 2020,
          "montant": 345558817,
          "eur_hab": 1217.8
        },
        {
          "year": 2021,
          "montant": 370307742,
          "eur_hab": 1287.9
        },
        {
          "year": 2022,
          "montant": 384121599,
          "eur_hab": 1324.1
        },
        {
          "year": 2023,
          "montant": 412274444,
          "eur_hab": 1404.5
        },
        {
          "year": 2024,
          "montant": 418209593,
          "eur_hab": 1421.4
        }
      ],
      "recettes_fonctionnement": [
        {
          "year": 2017,
          "montant": 381539633,
          "eur_hab": 1359.3
        },
        {
          "year": 2018,
          "montant": 389423410,
          "eur_hab": 1383.3
        },
        {
          "year": 2019,
          "montant": 395290947,
          "eur_hab": 1394.3
        },
        {
          "year": 2020,
          "montant": 387299908,
          "eur_hab": 1365.0
        },
        {
          "year": 2021,
          "montant": 409138968,
          "eur_hab": 1422.9
        },
        {
          "year": 2022,
          "montant": 441248790,
          "eur_hab": 1521.0
        },
        {
          "year": 2023,
          "montant": 448514359,
          "eur_hab": 1528.0
        },
        {
          "year": 2024,
          "montant": 455815235,
          "eur_hab": 1549.2
        }
      ],
      "depenses_investissement": [
        {
          "year": 2017,
          "montant": 95170918,
          "eur_hab": 339.1
        },
        {
          "year": 2018,
          "montant": 99060547,
          "eur_hab": 351.9
        },
        {
          "year": 2019,
          "montant": 125063655,
          "eur_hab": 441.1
        },
        {
          "year": 2020,
          "montant": 119479373,
          "eur_hab": 421.1
        },
        {
          "year": 2021,
          "montant": 115893021,
          "eur_hab": 403.1
        },
        {
          "year": 2022,
          "montant": 130019820,
          "eur_hab": 448.2
        },
        {
          "year": 2023,
          "montant": 152636038,
          "eur_hab": 520.0
        },
        {
          "year": 2024,
          "montant": 144716439,
          "eur_hab": 491.8
        }
      ],
      "impots_locaux": [
        {
          "year": 2017,
          "montant": 229659524,
          "eur_hab": 818.2
        },
        {
          "year": 2018,
          "montant": 233462187,
          "eur_hab": 829.3
        },
        {
          "year": 2019,
          "montant": 238218367,
          "eur_hab": 840.2
        },
        {
          "year": 2020,
          "montant": 242898322,
          "eur_hab": 856.0
        },
        {
          "year": 2021,
          "montant": 253808746,
          "eur_hab": 882.7
        },
        {
          "year": 2022,
          "montant": 258471801,
          "eur_hab": 891.0
        },
        {
          "year": 2023,
          "montant": 281279940,
          "eur_hab": 958.2
        },
        {
          "year": 2024,
          "montant": 284994356,
          "eur_hab": 968.6
        }
      ],
      "concours_etat": [
        {
          "year": 2017,
          "montant": 50395098,
          "eur_hab": 179.5
        },
        {
          "year": 2018,
          "montant": 51505309,
          "eur_hab": 183.0
        },
        {
          "year": 2019,
          "montant": 52881562,
          "eur_hab": 186.5
        },
        {
          "year": 2020,
          "montant": 54301932,
          "eur_hab": 191.4
        },
        {
          "year": 2021,
          "montant": 55551430,
          "eur_hab": 193.2
        },
        {
          "year": 2022,
          "montant": 57378748,
          "eur_hab": 197.8
        },
        {
          "year": 2023,
          "montant": 60053066,
          "eur_hab": 204.6
        },
        {
          "year": 2024,
          "montant": 62980418,
          "eur_hab": 214.1
        }
      ],
      "fiscalite_reversee": [
        {
          "year": 2017,
          "montant": 68754672,
          "eur_hab": 245.0
        },
        {
          "year": 2018,
          "montant": 68884037,
          "eur_hab": 244.7
        },
        {
          "year": 2019,
          "montant": 68937546,
          "eur_hab": 243.2
        },
        {
          "year": 2020,
          "montant": 69069830,
          "eur_hab": 243.4
        },
        {
          "year": 2021,
          "montant": 69228905,
          "eur_hab": 240.8
        },
        {
          "year": 2022,
          "montant": 69290720,
          "eur_hab": 238.8
        },
        {
          "year": 2023,
          "montant": 68886527,
          "eur_hab": 234.7
        },
        {
          "year": 2024,
          "montant": 68927654,
          "eur_hab": 234.3
        }
      ],
      "ventes_services": [
        {
          "year": 2017,
          "montant": 18258881,
          "eur_hab": 65.1
        },
        {
          "year": 2018,
          "montant": 27287700,
          "eur_hab": 96.9
        },
        {
          "year": 2019,
          "montant": 32656166,
          "eur_hab": 115.2
        },
        {
          "year": 2020,
          "montant": 21902668,
          "eur_hab": 77.2
        },
        {
          "year": 2021,
          "montant": 25023532,
          "eur_hab": 87.0
        },
        {
          "year": 2022,
          "montant": 29334776,
          "eur_hab": 101.1
        },
        {
          "year": 2023,
          "montant": 31069341,
          "eur_hab": 105.8
        },
        {
          "year": 2024,
          "montant": 33567346,
          "eur_hab": 114.1
        }
      ],
      "subventions_recues": [
        {
          "year": 2017,
          "montant": 33360365,
          "eur_hab": 118.9
        },
        {
          "year": 2018,
          "montant": 32285913,
          "eur_hab": 114.7
        },
        {
          "year": 2019,
          "montant": 31694031,
          "eur_hab": 111.8
        },
        {
          "year": 2020,
          "montant": 32626196,
          "eur_hab": 115.0
        },
        {
          "year": 2021,
          "montant": 33320487,
          "eur_hab": 115.9
        },
        {
          "year": 2022,
          "montant": 34310376,
          "eur_hab": 118.3
        },
        {
          "year": 2023,
          "montant": 35865323,
          "eur_hab": 122.2
        },
        {
          "year": 2024,
          "montant": 34900074,
          "eur_hab": 118.6
        }
      ],
      "frais_personnel": [
        {
          "year": 2017,
          "montant": 198412826,
          "eur_hab": 706.9
        },
        {
          "year": 2018,
          "montant": 198147178,
          "eur_hab": 703.9
        },
        {
          "year": 2019,
          "montant": 199890636,
          "eur_hab": 705.0
        },
        {
          "year": 2020,
          "montant": 191391382,
          "eur_hab": 674.5
        },
        {
          "year": 2021,
          "montant": 200003214,
          "eur_hab": 695.6
        },
        {
          "year": 2022,
          "montant": 206671536,
          "eur_hab": 712.4
        },
        {
          "year": 2023,
          "montant": 213057333,
          "eur_hab": 725.8
        },
        {
          "year": 2024,
          "montant": 219966052,
          "eur_hab": 747.6
        }
      ],
      "achats_charges": [
        {
          "year": 2017,
          "montant": 73616657,
          "eur_hab": 262.3
        },
        {
          "year": 2018,
          "montant": 77222823,
          "eur_hab": 274.3
        },
        {
          "year": 2019,
          "montant": 80295189,
          "eur_hab": 283.2
        },
        {
          "year": 2020,
          "montant": 71090145,
          "eur_hab": 250.5
        },
        {
          "year": 2021,
          "montant": 86261222,
          "eur_hab": 300.0
        },
        {
          "year": 2022,
          "montant": 91079596,
          "eur_hab": 314.0
        },
        {
          "year": 2023,
          "montant": 108713035,
          "eur_hab": 370.4
        },
        {
          "year": 2024,
          "montant": 103465849,
          "eur_hab": 351.7
        }
      ],
      "depenses_intervention": [
        {
          "year": 2017,
          "montant": 60680920,
          "eur_hab": 216.2
        },
        {
          "year": 2018,
          "montant": 60487961,
          "eur_hab": 214.9
        },
        {
          "year": 2019,
          "montant": 62347632,
          "eur_hab": 219.9
        },
        {
          "year": 2020,
          "montant": 72442281,
          "eur_hab": 255.3
        },
        {
          "year": 2021,
          "montant": 71738907,
          "eur_hab": 249.5
        },
        {
          "year": 2022,
          "montant": 50882747,
          "eur_hab": 175.4
        },
        {
          "year": 2023,
          "montant": 66074134,
          "eur_hab": 225.1
        },
        {
          "year": 2024,
          "montant": 75675294,
          "eur_hab": 257.2
        }
      ],
      "charges_financieres": [
        {
          "year": 2017,
          "montant": 3222500,
          "eur_hab": 11.5
        },
        {
          "year": 2018,
          "montant": 2845713,
          "eur_hab": 10.1
        },
        {
          "year": 2019,
          "montant": 2478675,
          "eur_hab": 8.7
        },
        {
          "year": 2020,
          "montant": 2339588,
          "eur_hab": 8.2
        },
        {
          "year": 2021,
          "montant": 2190136,
          "eur_hab": 7.6
        },
        {
          "year": 2022,
          "montant": 2429845,
          "eur_hab": 8.4
        },
        {
          "year": 2023,
          "montant": 7510998,
          "eur_hab": 25.6
        },
        {
          "year": 2024,
          "montant": 10322945,
          "eur_hab": 35.1
        }
      ],
      "depenses_equipement": [
        {
          "year": 2017,
          "montant": 54231802,
          "eur_hab": 193.2
        },
        {
          "year": 2018,
          "montant": 67105490,
          "eur_hab": 238.4
        },
        {
          "year": 2019,
          "montant": 88074172,
          "eur_hab": 310.7
        },
        {
          "year": 2020,
          "montant": 77233027,
          "eur_hab": 272.2
        },
        {
          "year": 2021,
          "montant": 79210227,
          "eur_hab": 275.5
        },
        {
          "year": 2022,
          "montant": 91653799,
          "eur_hab": 315.9
        },
        {
          "year": 2023,
          "montant": 107283675,
          "eur_hab": 365.5
        },
        {
          "year": 2024,
          "montant": 98644813,
          "eur_hab": 335.3
        }
      ],
      "subventions_equipement": [
        {
          "year": 2017,
          "montant": 9697938,
          "eur_hab": 34.6
        },
        {
          "year": 2018,
          "montant": 5549270,
          "eur_hab": 19.7
        },
        {
          "year": 2019,
          "montant": 13862309,
          "eur_hab": 48.9
        },
        {
          "year": 2020,
          "montant": 15817087,
          "eur_hab": 55.7
        },
        {
          "year": 2021,
          "montant": 12279059,
          "eur_hab": 42.7
        },
        {
          "year": 2022,
          "montant": 12997499,
          "eur_hab": 44.8
        },
        {
          "year": 2023,
          "montant": 16082551,
          "eur_hab": 54.8
        },
        {
          "year": 2024,
          "montant": 13987518,
          "eur_hab": 47.5
        }
      ],
      "remboursements_emprunts": [
        {
          "year": 2017,
          "montant": 26669174,
          "eur_hab": 95.0
        },
        {
          "year": 2018,
          "montant": 25042467,
          "eur_hab": 89.0
        },
        {
          "year": 2019,
          "montant": 21087297,
          "eur_hab": 74.4
        },
        {
          "year": 2020,
          "montant": 20714987,
          "eur_hab": 73.0
        },
        {
          "year": 2021,
          "montant": 23010724,
          "eur_hab": 80.0
        },
        {
          "year": 2022,
          "montant": 24635461,
          "eur_hab": 84.9
        },
        {
          "year": 2023,
          "montant": 27880299,
          "eur_hab": 95.0
        },
        {
          "year": 2024,
          "montant": 29929547,
          "eur_hab": 101.7
        }
      ]
    }
  },
  "kpi_labels_fr": {
    "recettes_totales": "Recettes totales hors emprunts",
    "depenses_totales": "Dépenses totales hors remb.",
    "encours_dette": "Encours de dette",
    "epargne_brute": "Épargne brute",
    "capacite_financement": "Capacité ou besoin de financement",
    "depenses_fonctionnement": "Dépenses de fonctionnement",
    "recettes_fonctionnement": "Recettes de fonctionnement",
    "depenses_investissement": "Dépenses d'investissement",
    "impots_locaux": "Impôts locaux",
    "concours_etat": "Concours de l'État",
    "fiscalite_reversee": "Fiscalité reversée",
    "ventes_services": "Ventes de biens et services",
    "subventions_recues": "Subventions reçues",
    "frais_personnel": "Frais de personnel",
    "achats_charges": "Achats et charges externes",
    "depenses_intervention": "Dépenses d'intervention",
    "charges_financieres": "Charges financières",
    "depenses_equipement": "Dépenses d'équipement",
    "subventions_equipement": "Subventions d'équipement versées",
    "remboursements_emprunts": "Remboursements d'emprunts"
  },
  "kpi_labels_en": {
    "recettes_totales": "Total revenue (excl. borrowing)",
    "depenses_totales": "Total expenditure",
    "encours_dette": "Debt outstanding",
    "epargne_brute": "Gross savings",
    "capacite_financement": "Financing capacity / needs",
    "depenses_fonctionnement": "Operating expenditure",
    "recettes_fonctionnement": "Operating revenue",
    "depenses_investissement": "Capital expenditure",
    "impots_locaux": "Local taxes",
    "concours_etat": "State transfers",
    "fiscalite_reversee": "Tax sharing",
    "ventes_services": "Sales of goods & services",
    "subventions_recues": "Subsidies received",
    "frais_personnel": "Personnel costs",
    "achats_charges": "External purchases",
    "depenses_intervention": "Intervention spending",
    "charges_financieres": "Financial charges",
    "depenses_equipement": "Capital spending (equipment)",
    "subventions_equipement": "Capital subsidies paid",
    "remboursements_emprunts": "Loan repayments"
  }
}